Metadata-Version: 1.1
Name: nerparser
Version: 0.0.1
Summary: Resume parser using spacy named entity recognition
Home-page: UNKNOWN
Author: Mohamed Amine Bouslimi
Author-email: aminobouslimi@gmail.com
License: MIT
Keywords: CVParser
Platform: UNKNOWN
Classifier: Development Status :: 5 - Production/Stable
Classifier: Intended Audience :: Education
Classifier: Operating System :: Microsoft :: Windows :: Windows 10
Classifier: License :: OSI Approved :: MIT License
Classifier: Programming Language :: Python :: 3
